odoo/addons/procurement_purchase_requisition_generation_dropshipping/README.rst
odoo/addons/procurement_purchase_requisition_generation_dropshipping/__init__.py
odoo/addons/procurement_purchase_requisition_generation_dropshipping/__manifest__.py
odoo/addons/procurement_purchase_requisition_generation_dropshipping/i18n/it.po
odoo/addons/procurement_purchase_requisition_generation_dropshipping/i18n/procurement_purchase_requisition_generation_dropshipping.pot
odoo/addons/procurement_purchase_requisition_generation_dropshipping/models/__init__.py
odoo/addons/procurement_purchase_requisition_generation_dropshipping/models/purchase_order.py
odoo/addons/procurement_purchase_requisition_generation_dropshipping/models/purchase_requisition_line.py
odoo/addons/procurement_purchase_requisition_generation_dropshipping/models/stock_rule.py
odoo/addons/procurement_purchase_requisition_generation_dropshipping/readme/CONTRIBUTORS.md
odoo/addons/procurement_purchase_requisition_generation_dropshipping/readme/DESCRIPTION.md
odoo/addons/procurement_purchase_requisition_generation_dropshipping/readme/USAGE.md
odoo/addons/procurement_purchase_requisition_generation_dropshipping/static/description/icon.png
odoo/addons/procurement_purchase_requisition_generation_dropshipping/static/description/index.html
odoo/addons/procurement_purchase_requisition_generation_dropshipping/tests/__init__.py
odoo/addons/procurement_purchase_requisition_generation_dropshipping/tests/test_purchase_requisition_stock_dropshipping.py
odoo/addons/procurement_purchase_requisition_generation_dropshipping/views/purchase_views.xml
odoo_addon_procurement_purchase_requisition_generation_dropshipping-17.0.1.0.0.4.dist-info/METADATA
odoo_addon_procurement_purchase_requisition_generation_dropshipping-17.0.1.0.0.4.dist-info/WHEEL
odoo_addon_procurement_purchase_requisition_generation_dropshipping-17.0.1.0.0.4.dist-info/top_level.txt
odoo_addon_procurement_purchase_requisition_generation_dropshipping-17.0.1.0.0.4.dist-info/RECORD
