Metadata-Version: 2.1
Name: odoo-addon-procurement_purchase_requisition_generation_dropshipping
Version: 17.0.1.0.0.4
Requires-Python: >=3.10
Requires-Dist: odoo-addon-procurement_purchase_requisition_generation>=17.0dev,<17.1dev
Requires-Dist: odoo>=17.0a,<17.1dev
Summary: Procurement purchase requisition dropshipping
Home-page: https://github.com/OCA/purchase-workflow
License: AGPL-3
Author: Odoo Community Association (OCA)
Author-email: support@odoo-community.org
Classifier: Programming Language :: Python
Classifier: Framework :: Odoo
Classifier: Framework :: Odoo :: 17.0
Classifier: License :: OSI Approved :: GNU Affero General Public License v3
